strkernel/__init__.py
strkernel/gappy_kernel.py
strkernel/gappy_trie.py
strkernel/mismatch_kernel.py
strkernel/motif_kernel.py
strkernel/motifkernel.py
strkernel/lib/MismatchTrie.py
strkernel/lib/__init__.py
strkernel/lib/mismatchTrie.py
strkernel/lib/motif.py
strkernel/lib/motiftrie.py
strkernel/lib/trie.py
strkernel-0.2.dist-info/METADATA
strkernel-0.2.dist-info/RECORD
strkernel-0.2.dist-info/WHEEL
strkernel-0.2.dist-info/top_level.txt
tests/__init__.py
tests/test_mismatch_kernel.py
tests/test_motif_kernel.py
